{
  "red_bot": "code_killers_bot",
  "blue_bot": "dhoom_machala_bot",
  "winner": "red",
  "reason": "blue failed to return a move (no_output)",
  "total_moves": 1,
  "moves": [
    {
      "move_number": 0,
      "player": "red",
      "move": [
        0,
        0
      ],
      "time_taken": 0.980844,
      "remaining_time": 59.019156,
      "result": "ok",
      "board_after": [
        [
          [
            1,
            1
          ],
          [
            0,
            0
          ],
          [
            0,
            0
          ],
          [
            0,
            0
          ],
          [
            0,
            0
          ],
          [
            0,
            0
          ],
          [
            0,
            0
          ]
        ],
        [
          [
            0,
            0
          ],
          [
            0,
            0
          ],
          [
            0,
            0
          ],
          [
            0,
            0
          ],
          [
            0,
            0
          ],
          [
            0,
            0
          ],
          [
            0,
            0
          ]
        ],
        [
          [
            0,
            0
          ],
          [
            0,
            0
          ],
          [
            0,
            0
          ],
          [
            0,
            0
          ],
          [
            0,
            0
          ],
          [
            0,
            0
          ],
          [
            0,
            0
          ]
        ],
        [
          [
            0,
            0
          ],
          [
            0,
            0
          ],
          [
            0,
            0
          ],
          [
            0,
            0
          ],
          [
            0,
            0
          ],
          [
            0,
            0
          ],
          [
            0,
            0
          ]
        ],
        [
          [
            0,
            0
          ],
          [
            0,
            0
          ],
          [
            0,
            0
          ],
          [
            0,
            0
          ],
          [
            0,
            0
          ],
          [
            0,
            0
          ],
          [
            0,
            0
          ]
        ],
        [
          [
            0,
            0
          ],
          [
            0,
            0
          ],
          [
            0,
            0
          ],
          [
            0,
            0
          ],
          [
            0,
            0
          ],
          [
            0,
            0
          ],
          [
            0,
            0
          ]
        ],
        [
          [
            0,
            0
          ],
          [
            0,
            0
          ],
          [
            0,
            0
          ],
          [
            0,
            0
          ],
          [
            0,
            0
          ],
          [
            0,
            0
          ],
          [
            0,
            0
          ]
        ]
      ]
    },
    {
      "move_number": 1,
      "player": "blue",
      "move": null,
      "time_taken": 0.036331,
      "remaining_time": 59.963669,
      "result": "forfeit (no_output)",
      "board_after": null
    }
  ],
  "red_time_remaining": 59.019156,
  "blue_time_remaining": 59.963669
}